<?xml version="1.0" encoding="UTF-8"?><record_update>
    <sys_choice action="INSERT_OR_UPDATE" field="x_74235_tidal_ci_transition_type" table="cmdb_ci_business_app" version="3">
        <sys_choice_set action="INSERT_OR_UPDATE">
            <element>x_74235_tidal_ci_transition_type</element>
            <name>cmdb_ci_business_app</name>
            <sys_class_name>sys_choice_set</sys_class_name>
            <sys_created_by>admin</sys_created_by>
            <sys_created_on>2020-09-21 23:33:30</sys_created_on>
            <sys_id>f30904572f9b90101fb2e93df699b6d1</sys_id>
            <sys_mod_count>0</sys_mod_count>
            <sys_name>x_74235_tidal_ci_transition_type</sys_name>
            <sys_package display_value="Tidal CI Integration" source="x_74235_tidal_ci">323bb3022f3ed4101fb2e93df699b66c</sys_package>
            <sys_policy/>
            <sys_scope display_value="Tidal CI Integration">323bb3022f3ed4101fb2e93df699b66c</sys_scope>
            <sys_update_name>sys_choice_cmdb_ci_business_app_x_74235_tidal_ci_transition_type</sys_update_name>
            <sys_updated_by>admin</sys_updated_by>
            <sys_updated_on>2020-09-21 23:33:30</sys_updated_on>
        </sys_choice_set>
        <sys_choice action="INSERT_OR_UPDATE">
            <dependent_value/>
            <element>x_74235_tidal_ci_transition_type</element>
            <hint/>
            <inactive>false</inactive>
            <label>Refactor</label>
            <language>en</language>
            <name>cmdb_ci_business_app</name>
            <sequence>0</sequence>
            <sys_created_by>admin</sys_created_by>
            <sys_created_on>2020-09-21 23:33:30</sys_created_on>
            <sys_domain>global</sys_domain>
            <sys_domain_path>/</sys_domain_path>
            <sys_id>7b0904572f9b90101fb2e93df699b6d0</sys_id>
            <sys_mod_count>1</sys_mod_count>
            <sys_updated_by>admin</sys_updated_by>
            <sys_updated_on>2020-09-21 23:48:42</sys_updated_on>
            <value>refactor</value>
        </sys_choice>
        <sys_choice action="INSERT_OR_UPDATE">
            <dependent_value/>
            <element>x_74235_tidal_ci_transition_type</element>
            <hint/>
            <inactive>false</inactive>
            <label>Replatform</label>
            <language>en</language>
            <name>cmdb_ci_business_app</name>
            <sequence>1</sequence>
            <sys_created_by>admin</sys_created_by>
            <sys_created_on>2020-09-21 23:33:30</sys_created_on>
            <sys_domain>global</sys_domain>
            <sys_domain_path>/</sys_domain_path>
            <sys_id>ff0904572f9b90101fb2e93df699b6d4</sys_id>
            <sys_mod_count>1</sys_mod_count>
            <sys_updated_by>admin</sys_updated_by>
            <sys_updated_on>2020-09-21 23:48:47</sys_updated_on>
            <value>replatform</value>
        </sys_choice>
        <sys_choice action="INSERT_OR_UPDATE">
            <dependent_value/>
            <element>x_74235_tidal_ci_transition_type</element>
            <hint/>
            <inactive>false</inactive>
            <label>Repurchase</label>
            <language>en</language>
            <name>cmdb_ci_business_app</name>
            <sequence>2</sequence>
            <sys_created_by>admin</sys_created_by>
            <sys_created_on>2020-09-21 23:33:30</sys_created_on>
            <sys_domain>global</sys_domain>
            <sys_domain_path>/</sys_domain_path>
            <sys_id>730904572f9b90101fb2e93df699b6d9</sys_id>
            <sys_mod_count>1</sys_mod_count>
            <sys_updated_by>admin</sys_updated_by>
            <sys_updated_on>2020-09-21 23:48:52</sys_updated_on>
            <value>repurchase</value>
        </sys_choice>
        <sys_choice action="INSERT_OR_UPDATE">
            <dependent_value/>
            <element>x_74235_tidal_ci_transition_type</element>
            <hint/>
            <inactive>false</inactive>
            <label>Retain</label>
            <language>en</language>
            <name>cmdb_ci_business_app</name>
            <sequence>3</sequence>
            <sys_created_by>admin</sys_created_by>
            <sys_created_on>2020-09-22 00:08:54</sys_created_on>
            <sys_domain>global</sys_domain>
            <sys_domain_path>/</sys_domain_path>
            <sys_id>9621109f2f9b90101fb2e93df699b6e7</sys_id>
            <sys_mod_count>2</sys_mod_count>
            <sys_updated_by>admin</sys_updated_by>
            <sys_updated_on>2020-09-22 00:48:56</sys_updated_on>
            <value>retain</value>
        </sys_choice>
    </sys_choice>
</record_update>
